vridge_tf/__init__.py
vridge_tf/data_processing.py
vridge_tf/model_utils.py
vridge_tf-0.0.1.dist-info/METADATA
vridge_tf-0.0.1.dist-info/WHEEL
vridge_tf-0.0.1.dist-info/top_level.txt
vridge_tf-0.0.1.dist-info/RECORD
